LICENSE
MANIFEST.in
README.md
setup.py
names_oracle/__init__.py
names_oracle/__main__.py
names_oracle.egg-info/PKG-INFO
names_oracle.egg-info/SOURCES.txt
names_oracle.egg-info/dependency_links.txt
names_oracle.egg-info/top_level.txt