Metadata-Version: 2.1
Name: names-oracle
Version: 0.2
Summary: Provides information and statistics about names and last names.
Home-page: https://github.com/leoli51/Names-Oracle
Author: Leonardo La Rocca
Author-email: leo_la_rocca@yahoo.it
License: MIT
Keywords: names database
Platform: UNKNOWN
License-File: LICENSE
